{"_type":"export","__export_format":4,"__export_date":"2025-03-19T01:02:36.420Z","__export_source":"insomnia.desktop.app:v10.3.1","resources":[{"_id":"req_f247dd9407d04a549e870a1b5b4496c7","parentId":"fld_950421e50fd44584ad81b0d6adcc041a","modified":1742346086987,"created":1742305169438,"url":"http://localhost:8080/auth/login","name":"Autenticação","description":"","method":"POST","body":{"mimeType":"application/json","text":"{\n    \"email\": \"ricardo.justino@exemplo.com\",\n    \"senha\": \"123\"\n}"},"parameters":[],"headers":[{"name":"Content-Type","value":"application/json"},{"name":"User-Agent","value":"insomnia/10.3.1"}],"authentication":{},"metaSortKey":-1742344865943,"isPrivate":false,"pathParameters":[],"settingStoreCookies":true,"settingSendCookies":true,"settingDisableRenderRequestBody":false,"settingEncodeUrl":true,"settingRebuildPath":true,"settingFollowRedirects":"global","_type":"request"},{"_id":"fld_950421e50fd44584ad81b0d6adcc041a","parentId":"wrk_ba408b070516419b801a2b64c181a5ae","modified":1742176794474,"created":1742176794474,"name":"monolito","description":"","environment":{},"environmentPropertyOrder":null,"metaSortKey":-1742176794474,"environmentType":"kv","_type":"request_group"},{"_id":"wrk_ba408b070516419b801a2b64c181a5ae","parentId":null,"modified":1742176762073,"created":1742176762073,"name":"Edugo","description":"","scope":"collection","_type":"workspace"},{"_id":"req_1763194f6b974f0ba7808301f05d9905","parentId":"fld_8ec7ebb232264af2a81577fd4e1ab578","modified":1742345544502,"created":1742344868761,"url":"http://localhost:8080/desempenhos","name":"Consultar todos Desempenhos","description":"","method":"GET","body":{},"parameters":[],"headers":[{"name":"User-Agent","value":"insomnia/10.3.1"}],"authentication":{},"metaSortKey":-1742344868761,"isPrivate":false,"pathParameters":[],"settingStoreCookies":true,"settingSendCookies":true,"settingDisableRenderRequestBody":false,"settingEncodeUrl":true,"settingRebuildPath":true,"settingFollowRedirects":"global","_type":"request"},{"_id":"fld_8ec7ebb232264af2a81577fd4e1ab578","parentId":"fld_950421e50fd44584ad81b0d6adcc041a","modified":1742344865843,"created":1742344865843,"name":"Desempenho","description":"","environment":{},"environmentPropertyOrder":null,"metaSortKey":-1742344865843,"environmentType":"kv","_type":"request_group"},{"_id":"req_ec9e73ee5177454ba4557d1d13995838","parentId":"fld_8ec7ebb232264af2a81577fd4e1ab578","modified":1742345574322,"created":1742345558029,"url":"http://localhost:8080/desempenhos/937ae0db-b739-4e8d-a2af-b2f36edb5b3f","name":"Consultar Desempenho","description":"","method":"GET","body":{},"parameters":[],"headers":[{"name":"User-Agent","value":"insomnia/10.3.1"}],"authentication":{},"metaSortKey":-1742325019099.5,"isPrivate":false,"pathParameters":[],"settingStoreCookies":true,"settingSendCookies":true,"settingDisableRenderRequestBody":false,"settingEncodeUrl":true,"settingRebuildPath":true,"settingFollowRedirects":"global","_type":"request"},{"_id":"req_42c70e3dbc27456fb4689797e1bcd45a","parentId":"fld_8ec7ebb232264af2a81577fd4e1ab578","modified":1742345738104,"created":1742345600965,"url":"http://localhost:8080/desempenhos/937ae0db-b739-4e8d-a2af-b2f36edb5b3f","name":"Atualizar Desempenho","description":"","method":"PUT","body":{"mimeType":"application/json","text":"{\n\t\"id\": \"937ae0db-b739-4e8d-a2af-b2f36edb5b3f\",\n\t\"aluno\": {\n\t\t\"id\": \"19094345-a2da-465b-aa42-246be6199151\",\n\t\t\"nome\": \"Ricardo Justino\"\n\t},\n\t\"disciplina\": {\n\t\t\"id\": 52,\n\t\t\"nome\": \"Desenvolvimento Web com Spring Boot\",\n\t\t\"valor\": 110.00\n\t},\n\t\"nota\": 7.5,\n\t\"faltas\": 5\n}"},"parameters":[],"headers":[{"name":"Content-Type","value":"application/json"},{"name":"User-Agent","value":"insomnia/10.3.1"}],"authentication":{},"metaSortKey":-1742315094268.75,"isPrivate":false,"pathParameters":[],"settingStoreCookies":true,"settingSendCookies":true,"settingDisableRenderRequestBody":false,"settingEncodeUrl":true,"settingRebuildPath":true,"settingFollowRedirects":"global","_type":"request"},{"_id":"req_00e8699c0c4f462d819c013fa515aade","parentId":"fld_8ec7ebb232264af2a81577fd4e1ab578","modified":1742345830603,"created":1742345811891,"url":"http://localhost:8080/desempenhos","name":"Criar Desempenho","description":"","method":"POST","body":{"mimeType":"application/json","text":"{\n\t\"aluno\": {\n\t\t\"id\": \"19094345-a2da-465b-aa42-246be6199151\",\n\t\t\"nome\": \"Ricardo Justino\"\n\t},\n\t\"disciplina\": {\n\t\t\"id\": 52,\n\t\t\"nome\": \"Desenvolvimento Web com Spring Boot\",\n\t\t\"valor\": 110.00\n\t},\n\t\"nota\": 7.5,\n\t\"faltas\": 9\n}"},"parameters":[],"headers":[{"name":"Content-Type","value":"application/json"},{"name":"User-Agent","value":"insomnia/10.3.1"}],"authentication":{},"metaSortKey":-1742315094218.75,"isPrivate":false,"pathParameters":[],"settingStoreCookies":true,"settingSendCookies":true,"settingDisableRenderRequestBody":false,"settingEncodeUrl":true,"settingRebuildPath":true,"settingFollowRedirects":"global","_type":"request"},{"_id":"req_d0c2cabc6871482b9bc90244661b29b4","parentId":"fld_8ec7ebb232264af2a81577fd4e1ab578","modified":1742345984839,"created":1742345582114,"url":"http://localhost:8080/desempenhos/eae4f39f-4622-4352-8310-7e9b2310ede6","name":"Excluir Desempenho","description":"","method":"DELETE","body":{},"parameters":[],"headers":[{"name":"User-Agent","value":"insomnia/10.3.1"}],"authentication":{},"metaSortKey":-1742315094168.75,"isPrivate":false,"pathParameters":[],"settingStoreCookies":true,"settingSendCookies":true,"settingDisableRenderRequestBody":false,"settingEncodeUrl":true,"settingRebuildPath":true,"settingFollowRedirects":"global","_type":"request"},{"_id":"req_a6819294da114f528961d69a9a341a36","parentId":"fld_7fca49ced4d947068f0b2a475398c12d","modified":1742307976928,"created":1742302827312,"url":"http://localhost:8080/cobrancas","name":"Consultar todas Cobranças","description":"","method":"GET","body":{},"parameters":[],"headers":[{"name":"User-Agent","value":"insomnia/10.3.1"},{"name":"Authorization","value":"Bearer eyJhbGciOiJIUzI1NiJ9.eyJzdWIiOiJyaWNhcmRvLmp1c3Rpbm9AZXhlbXBsby5jb20iLCJpYXQiOjE3NDIzMDc1OTIsImV4cCI6MTc0MjM5Mzk5Mn0.wfVrflkPRjVDY0s5pJ2MUj6lslntifSSlrgCCTKQucE"}],"authentication":{},"metaSortKey":-1742302938011,"isPrivate":false,"pathParameters":[],"settingStoreCookies":true,"settingSendCookies":true,"settingDisableRenderRequestBody":false,"settingEncodeUrl":true,"settingRebuildPath":true,"settingFollowRedirects":"global","_type":"request"},{"_id":"fld_7fca49ced4d947068f0b2a475398c12d","parentId":"fld_950421e50fd44584ad81b0d6adcc041a","modified":1742302931022,"created":1742302931022,"name":"Cobrança","description":"","environment":{},"environmentPropertyOrder":null,"metaSortKey":-1742302931022,"environmentType":"kv","_type":"request_group"},{"_id":"req_eb161ac759a64744b75160ea05135b27","parentId":"fld_7fca49ced4d947068f0b2a475398c12d","modified":1742307975541,"created":1742302946525,"url":"http://localhost:8080/cobrancas/1044ffa9-1444-453f-b0d7-f5e3c4bd2b52","name":"Consultar Cobrança","description":"","method":"GET","body":{},"parameters":[],"headers":[{"name":"User-Agent","value":"insomnia/10.3.1"},{"name":"Authorization","value":"Bearer eyJhbGciOiJIUzI1NiJ9.eyJzdWIiOiJyaWNhcmRvLmp1c3Rpbm9AZXhlbXBsby5jb20iLCJpYXQiOjE3NDIzMDc1OTIsImV4cCI6MTc0MjM5Mzk5Mn0.wfVrflkPRjVDY0s5pJ2MUj6lslntifSSlrgCCTKQucE"}],"authentication":{},"metaSortKey":-1742299197681.5,"isPrivate":false,"pathParameters":[],"settingStoreCookies":true,"settingSendCookies":true,"settingDisableRenderRequestBody":false,"settingEncodeUrl":true,"settingRebuildPath":true,"settingFollowRedirects":"global","_type":"request"},{"_id":"req_1785a5d369d14da79b552b143341ab82","parentId":"fld_7fca49ced4d947068f0b2a475398c12d","modified":1742307973700,"created":1742303190120,"url":"http://localhost:8080/cobrancas/1044ffa9-1444-453f-b0d7-f5e3c4bd2b52","name":"Excluir Cobrança","description":"","method":"DELETE","body":{},"parameters":[],"headers":[{"name":"User-Agent","value":"insomnia/10.3.1"},{"name":"Authorization","value":"Bearer eyJhbGciOiJIUzI1NiJ9.eyJzdWIiOiJyaWNhcmRvLmp1c3Rpbm9AZXhlbXBsby5jb20iLCJpYXQiOjE3NDIzMDc1OTIsImV4cCI6MTc0MjM5Mzk5Mn0.wfVrflkPRjVDY0s5pJ2MUj6lslntifSSlrgCCTKQucE"}],"authentication":{},"metaSortKey":-1742299197581.5,"isPrivate":false,"pathParameters":[],"settingStoreCookies":true,"settingSendCookies":true,"settingDisableRenderRequestBody":false,"settingEncodeUrl":true,"settingRebuildPath":true,"settingFollowRedirects":"global","_type":"request"},{"_id":"req_cea838be38e24611a19dac065168f0de","parentId":"fld_b7ec86a49f8d42dc8ace61168ad1e05e","modified":1742322509364,"created":1742295457352,"url":"http://localhost:8080/pagamentos/gerar/93e37be3-32e8-42f5-969a-4de900697412","name":"Gerar Pagamento","description":"","method":"POST","body":{},"parameters":[],"headers":[{"name":"User-Agent","value":"insomnia/10.3.1"},{"name":"Authorization","value":"Bearer eyJhbGciOiJIUzI1NiJ9.eyJzdWIiOiJyaWNhcmRvLmp1c3Rpbm9AZXhlbXBsby5jb20iLCJpYXQiOjE3NDIzMDc1OTIsImV4cCI6MTc0MjM5Mzk5Mn0.wfVrflkPRjVDY0s5pJ2MUj6lslntifSSlrgCCTKQucE"}],"authentication":{},"metaSortKey":-1742295457352,"isPrivate":false,"pathParameters":[],"settingStoreCookies":true,"settingSendCookies":true,"settingDisableRenderRequestBody":false,"settingEncodeUrl":true,"settingRebuildPath":true,"settingFollowRedirects":"global","_type":"request"},{"_id":"fld_b7ec86a49f8d42dc8ace61168ad1e05e","parentId":"fld_950421e50fd44584ad81b0d6adcc041a","modified":1742295109526,"created":1742295109526,"name":"Pagamento","description":"","environment":{},"environmentPropertyOrder":null,"metaSortKey":-1742295109526,"environmentType":"kv","_type":"request_group"},{"_id":"req_fabc3edc2bb54d86943746e61f8d537e","parentId":"fld_b7ec86a49f8d42dc8ace61168ad1e05e","modified":1742307967636,"created":1742259234814,"url":"http://localhost:8080/pagamentos","name":"Consultar todos Pagamentos","description":"","method":"GET","body":{},"parameters":[],"headers":[{"name":"User-Agent","value":"insomnia/10.3.1"},{"name":"Authorization","value":"Bearer eyJhbGciOiJIUzI1NiJ9.eyJzdWIiOiJyaWNhcmRvLmp1c3Rpbm9AZXhlbXBsby5jb20iLCJpYXQiOjE3NDIzMDc1OTIsImV4cCI6MTc0MjM5Mzk5Mn0.wfVrflkPRjVDY0s5pJ2MUj6lslntifSSlrgCCTKQucE"}],"authentication":{},"metaSortKey":-1742295121541,"isPrivate":false,"pathParameters":[],"settingStoreCookies":true,"settingSendCookies":true,"settingDisableRenderRequestBody":false,"settingEncodeUrl":true,"settingRebuildPath":true,"settingFollowRedirects":"global","_type":"request"},{"_id":"req_48e4389c9213457fb782281da882dddc","parentId":"fld_b7ec86a49f8d42dc8ace61168ad1e05e","modified":1742307966355,"created":1742301934022,"url":"http://localhost:8080/pagamentos/2a9d8d3a-d04e-4b25-9585-cbf3a509746a","name":"Consultar Pagamento","description":"","method":"GET","body":{},"parameters":[],"headers":[{"name":"User-Agent","value":"insomnia/10.3.1"},{"name":"Authorization","value":"Bearer eyJhbGciOiJIUzI1NiJ9.eyJzdWIiOiJyaWNhcmRvLmp1c3Rpbm9AZXhlbXBsby5jb20iLCJpYXQiOjE3NDIzMDc1OTIsImV4cCI6MTc0MjM5Mzk5Mn0.wfVrflkPRjVDY0s5pJ2MUj6lslntifSSlrgCCTKQucE"}],"authentication":{},"metaSortKey":-1742284540399.5,"isPrivate":false,"pathParameters":[],"settingStoreCookies":true,"settingSendCookies":true,"settingDisableRenderRequestBody":false,"settingEncodeUrl":true,"settingRebuildPath":true,"settingFollowRedirects":"global","_type":"request"},{"_id":"req_4f21e6b81d8f47ff8a23292c91fa51db","parentId":"fld_b7ec86a49f8d42dc8ace61168ad1e05e","modified":1742307964210,"created":1742296202169,"url":"http://localhost:8080/pagamentos/f441c17d-a61f-4702-975d-bcefc41830e6","name":"Excluir Pagamento","description":"","method":"DELETE","body":{},"parameters":[],"headers":[{"name":"User-Agent","value":"insomnia/10.3.1"},{"name":"Authorization","value":"Bearer eyJhbGciOiJIUzI1NiJ9.eyJzdWIiOiJyaWNhcmRvLmp1c3Rpbm9AZXhlbXBsby5jb20iLCJpYXQiOjE3NDIzMDc1OTIsImV4cCI6MTc0MjM5Mzk5Mn0.wfVrflkPRjVDY0s5pJ2MUj6lslntifSSlrgCCTKQucE"}],"authentication":{},"metaSortKey":-1742273959258,"isPrivate":false,"pathParameters":[],"settingStoreCookies":true,"settingSendCookies":true,"settingDisableRenderRequestBody":false,"settingEncodeUrl":true,"settingRebuildPath":true,"settingFollowRedirects":"global","_type":"request"},{"_id":"req_f82ce817d6394f66ad2e8023e201748b","parentId":"fld_2e17cc771dc54fefa127845d15617080","modified":1742307960310,"created":1742252796975,"url":"http://localhost:8080/matriculas/aluno/cpf/222.654.987-00","name":"Consultar Matrícula por CPF","description":"","method":"GET","body":{},"parameters":[],"headers":[{"name":"User-Agent","value":"insomnia/10.3.1"},{"name":"Authorization","value":"Bearer eyJhbGciOiJIUzI1NiJ9.eyJzdWIiOiJyaWNhcmRvLmp1c3Rpbm9AZXhlbXBsby5jb20iLCJpYXQiOjE3NDIzMDc1OTIsImV4cCI6MTc0MjM5Mzk5Mn0.wfVrflkPRjVDY0s5pJ2MUj6lslntifSSlrgCCTKQucE"}],"authentication":{},"metaSortKey":-1742252796975,"isPrivate":false,"pathParameters":[],"settingStoreCookies":true,"settingSendCookies":true,"settingDisableRenderRequestBody":false,"settingEncodeUrl":true,"settingRebuildPath":true,"settingFollowRedirects":"global","_type":"request"},{"_id":"fld_2e17cc771dc54fefa127845d15617080","parentId":"fld_950421e50fd44584ad81b0d6adcc041a","modified":1742242351865,"created":1742242351865,"name":"Matricula","description":"","environment":{},"environmentPropertyOrder":null,"metaSortKey":-1742242351865,"environmentType":"kv","_type":"request_group"},{"_id":"req_d10faa2c88414d89b3c7ac7fafb91792","parentId":"fld_2e17cc771dc54fefa127845d15617080","modified":1742307958772,"created":1742242354299,"url":"http://localhost:8080/matriculas","name":"Consultar todas Matrículas","description":"","method":"GET","body":{},"parameters":[],"headers":[{"name":"User-Agent","value":"insomnia/10.3.1"},{"name":"Authorization","value":"Bearer eyJhbGciOiJIUzI1NiJ9.eyJzdWIiOiJyaWNhcmRvLmp1c3Rpbm9AZXhlbXBsby5jb20iLCJpYXQiOjE3NDIzMDc1OTIsImV4cCI6MTc0MjM5Mzk5Mn0.wfVrflkPRjVDY0s5pJ2MUj6lslntifSSlrgCCTKQucE"}],"authentication":{},"metaSortKey":-1742242354299,"isPrivate":false,"pathParameters":[],"settingStoreCookies":true,"settingSendCookies":true,"settingDisableRenderRequestBody":false,"settingEncodeUrl":true,"settingRebuildPath":true,"settingFollowRedirects":"global","_type":"request"},{"_id":"req_6b1530bd75234851bfee524b5096a9fe","parentId":"fld_2e17cc771dc54fefa127845d15617080","modified":1742307954349,"created":1742242412231,"url":"http://localhost:8080/matriculas/1","name":"Consultar Matrícula","description":"","method":"GET","body":{},"parameters":[],"headers":[{"name":"User-Agent","value":"insomnia/10.3.1"},{"name":"Authorization","value":"Bearer eyJhbGciOiJIUzI1NiJ9.eyJzdWIiOiJyaWNhcmRvLmp1c3Rpbm9AZXhlbXBsby5jb20iLCJpYXQiOjE3NDIzMDc1OTIsImV4cCI6MTc0MjM5Mzk5Mn0.wfVrflkPRjVDY0s5pJ2MUj6lslntifSSlrgCCTKQucE"}],"authentication":{},"metaSortKey":-1742242354199,"isPrivate":false,"pathParameters":[],"settingStoreCookies":true,"settingSendCookies":true,"settingDisableRenderRequestBody":false,"settingEncodeUrl":true,"settingRebuildPath":true,"settingFollowRedirects":"global","_type":"request"},{"_id":"req_77b2694de8ef4d7fa12c2b3f2df516a4","parentId":"fld_2e17cc771dc54fefa127845d15617080","modified":1742322202625,"created":1742242535693,"url":"http://localhost:8080/matriculas","name":"Criar Matrícula","description":"","method":"POST","body":{"mimeType":"application/json","text":"  {\n    \"aluno\": {\n      \"id\": \"93e37be3-32e8-42f5-969a-4de900697412\"\n    },\n    \"disciplina\": {\n      \"id\": [ 169, 170, 171, 172, 173 ]\n    },\n    \"dataMatricula\": \"2025-03-17\",\n    \"status\": \"ATIVO\"\n  }"},"parameters":[],"headers":[{"name":"Content-Type","value":"application/json"},{"name":"User-Agent","value":"insomnia/10.3.1"},{"name":"Authorization","value":"Bearer eyJhbGciOiJIUzI1NiJ9.eyJzdWIiOiJyaWNhcmRvLmp1c3Rpbm9AZXhlbXBsby5jb20iLCJpYXQiOjE3NDIzMDc1OTIsImV4cCI6MTc0MjM5Mzk5Mn0.wfVrflkPRjVDY0s5pJ2MUj6lslntifSSlrgCCTKQucE"}],"authentication":{},"metaSortKey":-1742242354099,"isPrivate":false,"pathParameters":[],"settingStoreCookies":true,"settingSendCookies":true,"settingDisableRenderRequestBody":false,"settingEncodeUrl":true,"settingRebuildPath":true,"settingFollowRedirects":"global","_type":"request"},{"_id":"req_3eb4971a005f43b18f45c3c9abf25678","parentId":"fld_2e17cc771dc54fefa127845d15617080","modified":1742307951253,"created":1742256178481,"url":"http://localhost:8080/matriculas/302","name":"Alterar Matrícula","description":"","method":"PUT","body":{"mimeType":"application/json","text":"{\n  \"aluno\": {\n    \"id\": \"19094345-a2da-465b-aa42-246be6199151\"\n  },\n  \"disciplina\": {\n    \"id\": 161\n  },\n  \"dataMatricula\": \"2025-03-13\",\n  \"status\": \"ATIVO\"\n}"},"parameters":[],"headers":[{"name":"Content-Type","value":"application/json"},{"name":"User-Agent","value":"insomnia/10.3.1"},{"name":"Authorization","value":"Bearer eyJhbGciOiJIUzI1NiJ9.eyJzdWIiOiJyaWNhcmRvLmp1c3Rpbm9AZXhlbXBsby5jb20iLCJpYXQiOjE3NDIzMDc1OTIsImV4cCI6MTc0MjM5Mzk5Mn0.wfVrflkPRjVDY0s5pJ2MUj6lslntifSSlrgCCTKQucE"}],"authentication":{},"metaSortKey":-1742242354049,"isPrivate":false,"pathParameters":[],"settingStoreCookies":true,"settingSendCookies":true,"settingDisableRenderRequestBody":false,"settingEncodeUrl":true,"settingRebuildPath":true,"settingFollowRedirects":"global","_type":"request"},{"_id":"req_5f81b956156f4363bf44f716326a8c92","parentId":"fld_2e17cc771dc54fefa127845d15617080","modified":1742307949559,"created":1742242559832,"url":"http://localhost:8080/matriculas/402","name":"Excluir Matrícula","description":"","method":"DELETE","body":{},"parameters":[],"headers":[{"name":"User-Agent","value":"insomnia/10.3.1"},{"name":"Authorization","value":"Bearer eyJhbGciOiJIUzI1NiJ9.eyJzdWIiOiJyaWNhcmRvLmp1c3Rpbm9AZXhlbXBsby5jb20iLCJpYXQiOjE3NDIzMDc1OTIsImV4cCI6MTc0MjM5Mzk5Mn0.wfVrflkPRjVDY0s5pJ2MUj6lslntifSSlrgCCTKQucE"}],"authentication":{},"metaSortKey":-1742242353999,"isPrivate":false,"pathParameters":[],"settingStoreCookies":true,"settingSendCookies":true,"settingDisableRenderRequestBody":false,"settingEncodeUrl":true,"settingRebuildPath":true,"settingFollowRedirects":"global","_type":"request"},{"_id":"req_deb7d5792b404809ac51618e9997428a","parentId":"fld_185225b26837412db2b143ad045c1bd4","modified":1742307945958,"created":1742222901084,"url":"http://localhost:8080/disciplinas","name":"Consultar todas Disciplinas","description":"","method":"GET","body":{},"parameters":[],"headers":[{"name":"User-Agent","value":"insomnia/10.3.1"},{"name":"Authorization","value":"Bearer eyJhbGciOiJIUzI1NiJ9.eyJzdWIiOiJyaWNhcmRvLmp1c3Rpbm9AZXhlbXBsby5jb20iLCJpYXQiOjE3NDIzMDc1OTIsImV4cCI6MTc0MjM5Mzk5Mn0.wfVrflkPRjVDY0s5pJ2MUj6lslntifSSlrgCCTKQucE"}],"authentication":{},"metaSortKey":-1742222901084,"isPrivate":false,"pathParameters":[],"settingStoreCookies":true,"settingSendCookies":true,"settingDisableRenderRequestBody":false,"settingEncodeUrl":true,"settingRebuildPath":true,"settingFollowRedirects":"global","_type":"request"},{"_id":"fld_185225b26837412db2b143ad045c1bd4","parentId":"fld_950421e50fd44584ad81b0d6adcc041a","modified":1742222898901,"created":1742222898901,"name":"Disciplina","description":"","environment":{},"environmentPropertyOrder":null,"metaSortKey":-1742222898901,"environmentType":"kv","_type":"request_group"},{"_id":"req_9e14827096a54faab5af4b5d5b2d6395","parentId":"fld_185225b26837412db2b143ad045c1bd4","modified":1742307944649,"created":1742223045452,"url":"http://localhost:8080/disciplinas/1","name":"Consultar Disciplina","description":"","method":"GET","body":{},"parameters":[],"headers":[{"name":"User-Agent","value":"insomnia/10.3.1"},{"name":"Authorization","value":"Bearer eyJhbGciOiJIUzI1NiJ9.eyJzdWIiOiJyaWNhcmRvLmp1c3Rpbm9AZXhlbXBsby5jb20iLCJpYXQiOjE3NDIzMDc1OTIsImV4cCI6MTc0MjM5Mzk5Mn0.wfVrflkPRjVDY0s5pJ2MUj6lslntifSSlrgCCTKQucE"}],"authentication":{},"metaSortKey":-1742222900984,"isPrivate":false,"pathParameters":[],"settingStoreCookies":true,"settingSendCookies":true,"settingDisableRenderRequestBody":false,"settingEncodeUrl":true,"settingRebuildPath":true,"settingFollowRedirects":"global","_type":"request"},{"_id":"req_c8858d256b404c18bc5d713aa9a4f318","parentId":"fld_185225b26837412db2b143ad045c1bd4","modified":1742307943191,"created":1742223066768,"url":"http://localhost:8080/disciplinas","name":"Criar Disciplina","description":"","method":"POST","body":{"mimeType":"application/json","text":"{\n      \"nome\": \"Geografia e Tecnologia\",\n      \"descricao\": \"Aplicações da geografia na área de tecnologia.\",\n      \"nivel\": \"Geografia\",\n      \"valor\": 75.00,\n      \"professor\": {\n          \"id\": \"cba4a3db-c1ba-44f3-bd58-2b6c4df868c3\"\n      }\n  }"},"parameters":[],"headers":[{"name":"Content-Type","value":"application/json"},{"name":"User-Agent","value":"insomnia/10.3.1"},{"name":"Authorization","value":"Bearer eyJhbGciOiJIUzI1NiJ9.eyJzdWIiOiJyaWNhcmRvLmp1c3Rpbm9AZXhlbXBsby5jb20iLCJpYXQiOjE3NDIzMDc1OTIsImV4cCI6MTc0MjM5Mzk5Mn0.wfVrflkPRjVDY0s5pJ2MUj6lslntifSSlrgCCTKQucE"}],"authentication":{},"metaSortKey":-1742222900884,"isPrivate":false,"pathParameters":[],"settingStoreCookies":true,"settingSendCookies":true,"settingDisableRenderRequestBody":false,"settingEncodeUrl":true,"settingRebuildPath":true,"settingFollowRedirects":"global","_type":"request"},{"_id":"req_1841417a21f8412e8d882ca35ca2698a","parentId":"fld_185225b26837412db2b143ad045c1bd4","modified":1742307941742,"created":1742256070932,"url":"http://localhost:8080/disciplinas/1","name":"Atualizar Disciplina","description":"","method":"PUT","body":{"mimeType":"application/json","text":"{\n\t\"nome\": \"Algoritmos e Lógica de Programação\",\n\t\"descricao\": \"Fundamentos da construção de algoritmos e da lógica de programação.\",\n\t\"nivel\": \"Algoritmos\",\n\t\"valor\": 95.00,\n\t\"professor\": {\n\t\t\"id\": \"9e0d91bc-9553-4757-a5a3-63da54f6757d\"\n\t}\n}"},"parameters":[],"headers":[{"name":"Content-Type","value":"application/json"},{"name":"User-Agent","value":"insomnia/10.3.1"},{"name":"Authorization","value":"Bearer eyJhbGciOiJIUzI1NiJ9.eyJzdWIiOiJyaWNhcmRvLmp1c3Rpbm9AZXhlbXBsby5jb20iLCJpYXQiOjE3NDIzMDc1OTIsImV4cCI6MTc0MjM5Mzk5Mn0.wfVrflkPRjVDY0s5pJ2MUj6lslntifSSlrgCCTKQucE"}],"authentication":{},"metaSortKey":-1742222900834,"isPrivate":false,"pathParameters":[],"settingStoreCookies":true,"settingSendCookies":true,"settingDisableRenderRequestBody":false,"settingEncodeUrl":true,"settingRebuildPath":true,"settingFollowRedirects":"global","_type":"request"},{"_id":"req_22c47e297fcd44c59ff0064a6cc32746","parentId":"fld_185225b26837412db2b143ad045c1bd4","modified":1742307939958,"created":1742223088745,"url":"http://localhost:8080/disciplinas/1","name":"Excluir Disciplina","description":"","method":"DELETE","body":{},"parameters":[],"headers":[{"name":"User-Agent","value":"insomnia/10.3.1"},{"name":"Authorization","value":"Bearer eyJhbGciOiJIUzI1NiJ9.eyJzdWIiOiJyaWNhcmRvLmp1c3Rpbm9AZXhlbXBsby5jb20iLCJpYXQiOjE3NDIzMDc1OTIsImV4cCI6MTc0MjM5Mzk5Mn0.wfVrflkPRjVDY0s5pJ2MUj6lslntifSSlrgCCTKQucE"}],"authentication":{},"metaSortKey":-1742222900784,"isPrivate":false,"pathParameters":[],"settingStoreCookies":true,"settingSendCookies":true,"settingDisableRenderRequestBody":false,"settingEncodeUrl":true,"settingRebuildPath":true,"settingFollowRedirects":"global","_type":"request"},{"_id":"req_34272ce3a4884d40b9aa1b95b4221123","parentId":"fld_b456533f7ded4e3db0d416905a408455","modified":1742307936202,"created":1742222216858,"url":"http://localhost:8080/funcionarios","name":"Consultar todos Funcionários","description":"","method":"GET","body":{"mimeType":"application/json","text":""},"parameters":[],"headers":[{"name":"Content-Type","value":"application/json"},{"name":"User-Agent","value":"insomnia/10.3.1"},{"name":"Authorization","value":"Bearer eyJhbGciOiJIUzI1NiJ9.eyJzdWIiOiJyaWNhcmRvLmp1c3Rpbm9AZXhlbXBsby5jb20iLCJpYXQiOjE3NDIzMDc1OTIsImV4cCI6MTc0MjM5Mzk5Mn0.wfVrflkPRjVDY0s5pJ2MUj6lslntifSSlrgCCTKQucE"}],"authentication":{},"metaSortKey":-1742222216858,"isPrivate":false,"pathParameters":[],"settingStoreCookies":true,"settingSendCookies":true,"settingDisableRenderRequestBody":false,"settingEncodeUrl":true,"settingRebuildPath":true,"settingFollowRedirects":"global","_type":"request"},{"_id":"fld_b456533f7ded4e3db0d416905a408455","parentId":"fld_950421e50fd44584ad81b0d6adcc041a","modified":1742222212699,"created":1742222212699,"name":"Funcionario","description":"","environment":{},"environmentPropertyOrder":null,"metaSortKey":-1742222212699,"environmentType":"kv","_type":"request_group"},{"_id":"req_4cc51082c2b3445baefcbb7432157864","parentId":"fld_b456533f7ded4e3db0d416905a408455","modified":1742307934818,"created":1742222249410,"url":"http://localhost:8080/funcionarios/f478f6cb-7685-478d-a790-d83abdc6f1de","name":"Consultar Funcionário","description":"","method":"GET","body":{},"parameters":[],"headers":[{"name":"User-Agent","value":"insomnia/10.3.1"},{"name":"Authorization","value":"Bearer eyJhbGciOiJIUzI1NiJ9.eyJzdWIiOiJyaWNhcmRvLmp1c3Rpbm9AZXhlbXBsby5jb20iLCJpYXQiOjE3NDIzMDc1OTIsImV4cCI6MTc0MjM5Mzk5Mn0.wfVrflkPRjVDY0s5pJ2MUj6lslntifSSlrgCCTKQucE"}],"authentication":{},"metaSortKey":-1742222216758,"isPrivate":false,"pathParameters":[],"settingStoreCookies":true,"settingSendCookies":true,"settingDisableRenderRequestBody":false,"settingEncodeUrl":true,"settingRebuildPath":true,"settingFollowRedirects":"global","_type":"request"},{"_id":"req_a5d86d02dbcc43c6a949f2767321462c","parentId":"fld_b456533f7ded4e3db0d416905a408455","modified":1742307932981,"created":1742222280241,"url":"http://localhost:8080/funcionarios","name":"Criar Funcionário","description":"","method":"POST","body":{"mimeType":"application/json","text":"{\n        \"nome\": \"Diego Martins\",\n        \"cpf\": \"012.345.678-99\",\n        \"dataNascimento\": \"1984-02-27\",\n        \"email\": \"diego.martins@exemplo.com\",\n        \"telefone\": \"11955554444\",\n        \"endereco\": \"Avenida das Rosas, 1111\",\n        \"bairro\": \"Centro\",\n        \"cidade\": \"Porto Alegre\",\n        \"uf\": \"RS\",\n        \"cep\": \"56789-012\",\n        \"senha\": \"ijkl\",\n        \"dataContratacao\": \"2009-05-05\",\n        \"nivelAcesso\": 2\n    }"},"parameters":[],"headers":[{"name":"Content-Type","value":"application/json"},{"name":"User-Agent","value":"insomnia/10.3.1"},{"name":"Authorization","value":"Bearer eyJhbGciOiJIUzI1NiJ9.eyJzdWIiOiJyaWNhcmRvLmp1c3Rpbm9AZXhlbXBsby5jb20iLCJpYXQiOjE3NDIzMDc1OTIsImV4cCI6MTc0MjM5Mzk5Mn0.wfVrflkPRjVDY0s5pJ2MUj6lslntifSSlrgCCTKQucE"}],"authentication":{},"metaSortKey":-1742222216658,"isPrivate":false,"pathParameters":[],"settingStoreCookies":true,"settingSendCookies":true,"settingDisableRenderRequestBody":false,"settingEncodeUrl":true,"settingRebuildPath":true,"settingFollowRedirects":"global","_type":"request"},{"_id":"req_03943dbbad1641c4842a334fbafc5c02","parentId":"fld_b456533f7ded4e3db0d416905a408455","modified":1742307931359,"created":1742255348043,"url":"http://localhost:8080/funcionarios/718ccb3c-e243-4a5d-812d-8a361afdb8fd","name":"Atualizar Funcionário","description":"","method":"PUT","body":{"mimeType":"application/json","text":"{\n\t\"nome\": \"Julia Justino\",\n\t\"cpf\": \"444.654.987-00\",\n\t\"dataNascimento\": \"2000-01-01\",\n\t\"email\": \"julia.justino@exemplo.com\",\n\t\"telefone\": \"11955555555\",\n\t\"endereco\": \"Rua Cavalo, 33\",\n\t\"bairro\": \"Centro\",\n\t\"cidade\": \"São Paulo\",\n\t\"uf\": \"SP\",\n\t\"cep\": \"00000-010\",\n\t\"dataContratacao\": \"2022-01-01\",\n\t\"nivelAcesso\": 1\n}"},"parameters":[],"headers":[{"name":"Content-Type","value":"application/json"},{"name":"User-Agent","value":"insomnia/10.3.1"},{"name":"Authorization","value":"Bearer eyJhbGciOiJIUzI1NiJ9.eyJzdWIiOiJyaWNhcmRvLmp1c3Rpbm9AZXhlbXBsby5jb20iLCJpYXQiOjE3NDIzMDc1OTIsImV4cCI6MTc0MjM5Mzk5Mn0.wfVrflkPRjVDY0s5pJ2MUj6lslntifSSlrgCCTKQucE"}],"authentication":{},"metaSortKey":-1742222216608,"isPrivate":false,"pathParameters":[],"settingStoreCookies":true,"settingSendCookies":true,"settingDisableRenderRequestBody":false,"settingEncodeUrl":true,"settingRebuildPath":true,"settingFollowRedirects":"global","_type":"request"},{"_id":"req_68355089566b4eeb9512f8e2d2f948bf","parentId":"fld_b456533f7ded4e3db0d416905a408455","modified":1742307929402,"created":1742222507500,"url":"http://localhost:8080/funcionarios/8ae7f65c-79af-4bb2-817c-7675eb0d8ed5","name":"Excluir Funcionário","description":"","method":"DELETE","body":{},"parameters":[],"headers":[{"name":"User-Agent","value":"insomnia/10.3.1"},{"name":"Authorization","value":"Bearer eyJhbGciOiJIUzI1NiJ9.eyJzdWIiOiJyaWNhcmRvLmp1c3Rpbm9AZXhlbXBsby5jb20iLCJpYXQiOjE3NDIzMDc1OTIsImV4cCI6MTc0MjM5Mzk5Mn0.wfVrflkPRjVDY0s5pJ2MUj6lslntifSSlrgCCTKQucE"}],"authentication":{},"metaSortKey":-1742222216558,"isPrivate":false,"pathParameters":[],"settingStoreCookies":true,"settingSendCookies":true,"settingDisableRenderRequestBody":false,"settingEncodeUrl":true,"settingRebuildPath":true,"settingFollowRedirects":"global","_type":"request"},{"_id":"req_b1782f0147224cc687a76c11261d21ad","parentId":"fld_640ab2b807104670994e87622692bfa4","modified":1742307924799,"created":1742220029343,"url":"http://localhost:8080/professores","name":"Consultar todos Professores","description":"","method":"GET","body":{},"parameters":[],"headers":[{"name":"User-Agent","value":"insomnia/10.3.1"},{"name":"Authorization","value":"Bearer eyJhbGciOiJIUzI1NiJ9.eyJzdWIiOiJyaWNhcmRvLmp1c3Rpbm9AZXhlbXBsby5jb20iLCJpYXQiOjE3NDIzMDc1OTIsImV4cCI6MTc0MjM5Mzk5Mn0.wfVrflkPRjVDY0s5pJ2MUj6lslntifSSlrgCCTKQucE"}],"authentication":{},"metaSortKey":-1742220029343,"isPrivate":false,"pathParameters":[],"settingStoreCookies":true,"settingSendCookies":true,"settingDisableRenderRequestBody":false,"settingEncodeUrl":true,"settingRebuildPath":true,"settingFollowRedirects":"global","_type":"request"},{"_id":"fld_640ab2b807104670994e87622692bfa4","parentId":"fld_950421e50fd44584ad81b0d6adcc041a","modified":1742220021360,"created":1742220021360,"name":"Professor","description":"","environment":{},"environmentPropertyOrder":null,"metaSortKey":-1742220021360,"environmentType":"kv","_type":"request_group"},{"_id":"req_ad45d1559767498bbd6c05c281df9b1a","parentId":"fld_640ab2b807104670994e87622692bfa4","modified":1742307920378,"created":1742220062774,"url":"http://localhost:8080/professores/9e0d91bc-9553-4757-a5a3-63da54f6757d","name":"Consultar Professor","description":"","method":"GET","body":{},"parameters":[],"headers":[{"name":"User-Agent","value":"insomnia/10.3.1"},{"name":"Authorization","value":"Bearer eyJhbGciOiJIUzI1NiJ9.eyJzdWIiOiJyaWNhcmRvLmp1c3Rpbm9AZXhlbXBsby5jb20iLCJpYXQiOjE3NDIzMDc1OTIsImV4cCI6MTc0MjM5Mzk5Mn0.wfVrflkPRjVDY0s5pJ2MUj6lslntifSSlrgCCTKQucE"}],"authentication":{},"metaSortKey":-1742220029318,"isPrivate":false,"pathParameters":[],"settingStoreCookies":true,"settingSendCookies":true,"settingDisableRenderRequestBody":false,"settingEncodeUrl":true,"settingRebuildPath":true,"settingFollowRedirects":"global","_type":"request"},{"_id":"req_4ce2fa7aeff5490caa3b10713911aba4","parentId":"fld_640ab2b807104670994e87622692bfa4","modified":1742307918899,"created":1742220092208,"url":"http://localhost:8080/professores","name":"Criar Professor","description":"","method":"POST","body":{"mimeType":"application/json","text":"{\n        \"nome\": \"Julio Batista\",\n        \"cpf\": \"636.031.980-26\",\n        \"dataNascimento\": \"1997-11-03\",\n        \"email\": \"juliobat@techschool.com\",\n        \"telefone\": \"11994227890\",\n        \"endereco\": \"Avenida da Cloud, 11\",\n        \"bairro\": \"Cloud\",\n        \"cidade\": \"Barueri\",\n        \"uf\": \"SP\",\n        \"cep\": \"06480-000\",\n        \"formacao\": \"Sistemas para Internet\",\n        \"especialidade\": \"Cloud Computing\",\n        \"senha\": \"senha123\"\n    }"},"parameters":[],"headers":[{"name":"Content-Type","value":"application/json"},{"name":"User-Agent","value":"insomnia/10.3.1"},{"name":"Authorization","value":"Bearer eyJhbGciOiJIUzI1NiJ9.eyJzdWIiOiJyaWNhcmRvLmp1c3Rpbm9AZXhlbXBsby5jb20iLCJpYXQiOjE3NDIzMDc1OTIsImV4cCI6MTc0MjM5Mzk5Mn0.wfVrflkPRjVDY0s5pJ2MUj6lslntifSSlrgCCTKQucE"}],"authentication":{},"metaSortKey":-1742220029293,"isPrivate":false,"pathParameters":[],"settingStoreCookies":true,"settingSendCookies":true,"settingDisableRenderRequestBody":false,"settingEncodeUrl":true,"settingRebuildPath":true,"settingFollowRedirects":"global","_type":"request"},{"_id":"req_727dc07b2c9e44569384435e16866523","parentId":"fld_640ab2b807104670994e87622692bfa4","modified":1742307917170,"created":1742254318133,"url":"http://localhost:8080/professores/c3e524fa-c93c-455f-b386-705c2b353950","name":"Atualizar Professor","description":"","method":"PUT","body":{"mimeType":"application/json","text":"{\n\t\t\"nome\": \"Julio Batista\",\n\t\t\"cpf\": \"636.031.980-26\",\n\t\t\"dataNascimento\": \"1997-11-30\",\n\t\t\"email\": \"juliobat@techschool.com\",\n\t\t\"telefone\": \"11994227890\",\n\t\t\"endereco\": \"Avenida da Cloud, 11\",\n\t\t\"bairro\": \"Cloud\",\n\t\t\"cidade\": \"Barueri\",\n\t\t\"uf\": \"SP\",\n\t\t\"cep\": \"06480-020\",\n\t\t\"formacao\": \"Sistemas para Internet\",\n\t\t\"especialidade\": \"Cloud Computing\"\n}"},"parameters":[],"headers":[{"name":"Content-Type","value":"application/json"},{"name":"User-Agent","value":"insomnia/10.3.1"},{"name":"Authorization","value":"Bearer eyJhbGciOiJIUzI1NiJ9.eyJzdWIiOiJyaWNhcmRvLmp1c3Rpbm9AZXhlbXBsby5jb20iLCJpYXQiOjE3NDIzMDc1OTIsImV4cCI6MTc0MjM5Mzk5Mn0.wfVrflkPRjVDY0s5pJ2MUj6lslntifSSlrgCCTKQucE"}],"authentication":{},"metaSortKey":-1742220029268,"isPrivate":false,"pathParameters":[],"settingStoreCookies":true,"settingSendCookies":true,"settingDisableRenderRequestBody":false,"settingEncodeUrl":true,"settingRebuildPath":true,"settingFollowRedirects":"global","_type":"request"},{"_id":"req_2a4d19ee5dfa4f88a773c20c78450ac1","parentId":"fld_640ab2b807104670994e87622692bfa4","modified":1742307914794,"created":1742220117978,"url":"http://localhost:8080/professores/149a29f1-8f1b-4940-94b7-ab039fbdb369","name":"Excluir Professor","description":"","method":"DELETE","body":{},"parameters":[],"headers":[{"name":"User-Agent","value":"insomnia/10.3.1"},{"name":"Authorization","value":"Bearer eyJhbGciOiJIUzI1NiJ9.eyJzdWIiOiJyaWNhcmRvLmp1c3Rpbm9AZXhlbXBsby5jb20iLCJpYXQiOjE3NDIzMDc1OTIsImV4cCI6MTc0MjM5Mzk5Mn0.wfVrflkPRjVDY0s5pJ2MUj6lslntifSSlrgCCTKQucE"}],"authentication":{},"metaSortKey":-1742220029243,"isPrivate":false,"pathParameters":[],"settingStoreCookies":true,"settingSendCookies":true,"settingDisableRenderRequestBody":false,"settingEncodeUrl":true,"settingRebuildPath":true,"settingFollowRedirects":"global","_type":"request"},{"_id":"req_d95901fbb2184d8c9f0ede74f70d964e","parentId":"fld_c799844c9882453d99e7aaae5cf22681","modified":1742307843129,"created":1742176798389,"url":"http://localhost:8080/alunos","name":"Consultar todos Alunos","description":"","method":"GET","body":{},"parameters":[],"headers":[{"name":"User-Agent","value":"insomnia/10.3.1"},{"name":"Authorization","value":"Bearer eyJhbGciOiJIUzI1NiJ9.eyJzdWIiOiJyaWNhcmRvLmp1c3Rpbm9AZXhlbXBsby5jb20iLCJpYXQiOjE3NDIzMDc1OTIsImV4cCI6MTc0MjM5Mzk5Mn0.wfVrflkPRjVDY0s5pJ2MUj6lslntifSSlrgCCTKQucE"}],"authentication":{},"metaSortKey":-1742176909121,"isPrivate":false,"pathParameters":[],"settingStoreCookies":true,"settingSendCookies":true,"settingDisableRenderRequestBody":false,"settingEncodeUrl":true,"settingRebuildPath":true,"settingFollowRedirects":"global","_type":"request"},{"_id":"fld_c799844c9882453d99e7aaae5cf22681","parentId":"fld_950421e50fd44584ad81b0d6adcc041a","modified":1742295145100,"created":1742176901330,"name":"Alunos","description":"","environment":{},"environmentPropertyOrder":null,"metaSortKey":-1742209215642.25,"environmentType":"kv","_type":"request_group"},{"_id":"req_063c70a8a2f3451f818a6eb4158c53f8","parentId":"fld_c799844c9882453d99e7aaae5cf22681","modified":1742307885855,"created":1742176915541,"url":"http://localhost:8080/alunos/19094345-a2da-465b-aa42-246be6199151","name":"Consultar Aluno","description":"","method":"GET","body":{},"parameters":[],"headers":[{"name":"User-Agent","value":"insomnia/10.3.1"},{"name":"Authorization","value":"Bearer eyJhbGciOiJIUzI1NiJ9.eyJzdWIiOiJyaWNhcmRvLmp1c3Rpbm9AZXhlbXBsby5jb20iLCJpYXQiOjE3NDIzMDc1OTIsImV4cCI6MTc0MjM5Mzk5Mn0.wfVrflkPRjVDY0s5pJ2MUj6lslntifSSlrgCCTKQucE"}],"authentication":{},"metaSortKey":-1742176909021,"isPrivate":false,"pathParameters":[],"settingStoreCookies":true,"settingSendCookies":true,"settingDisableRenderRequestBody":false,"settingEncodeUrl":true,"settingRebuildPath":true,"settingFollowRedirects":"global","_type":"request"},{"_id":"req_b8510d65bb374b1baac39a9fd744828c","parentId":"fld_c799844c9882453d99e7aaae5cf22681","modified":1742307890685,"created":1742176990537,"url":"http://localhost:8080/alunos","name":"Criar Aluno","description":"","method":"POST","body":{"mimeType":"application/json","text":"      {\n        \"nome\": \"Manoel Alves\",\n        \"cpf\": \"702.892.110-77\",\n        \"dataNascimento\": \"2002-12-16\",\n        \"email\": \"manealves@email.com\",\n        \"telefone\": \"11977232985\",\n        \"endereco\": \"Rua Mock, 123\",\n        \"bairro\": \"Bairro Mock\",\n        \"cidade\": \"Cidade Mock\",\n        \"uf\": \"SP\",\n        \"cep\": \"76852529\",\n        \"senha\": \"123\"\n      }"},"parameters":[],"headers":[{"name":"Content-Type","value":"application/json"},{"name":"User-Agent","value":"insomnia/10.3.1"},{"name":"Authorization","value":"Bearer eyJhbGciOiJIUzI1NiJ9.eyJzdWIiOiJyaWNhcmRvLmp1c3Rpbm9AZXhlbXBsby5jb20iLCJpYXQiOjE3NDIzMDc1OTIsImV4cCI6MTc0MjM5Mzk5Mn0.wfVrflkPRjVDY0s5pJ2MUj6lslntifSSlrgCCTKQucE"}],"authentication":{},"metaSortKey":-1742176908921,"isPrivate":false,"pathParameters":[],"settingStoreCookies":true,"settingSendCookies":true,"settingDisableRenderRequestBody":false,"settingEncodeUrl":true,"settingRebuildPath":true,"settingFollowRedirects":"global","_type":"request"},{"_id":"req_74d967ed0a7043f49931160820eb9a06","parentId":"fld_c799844c9882453d99e7aaae5cf22681","modified":1742307892700,"created":1742254415404,"url":"http://localhost:8080/alunos/93e37be3-32e8-42f5-969a-4de900697412","name":"Atualizar Aluno","description":"","method":"PUT","body":{"mimeType":"application/json","text":"{\n\t\"id\": \"93e37be3-32e8-42f5-969a-4de900697412\",\n\t\"nome\": \"Manoel Alves\",\n\t\"cpf\": \"70289211077\",\n\t\"dataNascimento\": \"2002-12-16\",\n\t\"email\": \"manealves@email.com\",\n\t\"telefone\": \"11977232985\",\n\t\"endereco\": \"Rua Mock, 123\",\n\t\"bairro\": \"Bairro Mock\",\n\t\"cidade\": \"Cidade Mock\",\n\t\"uf\": \"SP\",\n\t\"cep\": \"76852529\",\n\t\"matricula\": null\n}"},"parameters":[],"headers":[{"name":"Content-Type","value":"application/json"},{"name":"User-Agent","value":"insomnia/10.3.1"},{"name":"Authorization","value":"Bearer eyJhbGciOiJIUzI1NiJ9.eyJzdWIiOiJyaWNhcmRvLmp1c3Rpbm9AZXhlbXBsby5jb20iLCJpYXQiOjE3NDIzMDc1OTIsImV4cCI6MTc0MjM5Mzk5Mn0.wfVrflkPRjVDY0s5pJ2MUj6lslntifSSlrgCCTKQucE"}],"authentication":{},"metaSortKey":-1742176908871,"isPrivate":false,"pathParameters":[],"settingStoreCookies":true,"settingSendCookies":true,"settingDisableRenderRequestBody":false,"settingEncodeUrl":true,"settingRebuildPath":true,"settingFollowRedirects":"global","_type":"request"},{"_id":"req_01a2d74ed8c149c79bc1fdc7507f281b","parentId":"fld_c799844c9882453d99e7aaae5cf22681","modified":1742307893981,"created":1742180615815,"url":"http://localhost:8080/alunos/1b36b11f-27ff-445b-a0e2-3aa45650db97","name":"Excluir Aluno","description":"","method":"DELETE","body":{},"parameters":[],"headers":[{"name":"User-Agent","value":"insomnia/10.3.1"},{"name":"Authorization","value":"Bearer eyJhbGciOiJIUzI1NiJ9.eyJzdWIiOiJyaWNhcmRvLmp1c3Rpbm9AZXhlbXBsby5jb20iLCJpYXQiOjE3NDIzMDc1OTIsImV4cCI6MTc0MjM5Mzk5Mn0.wfVrflkPRjVDY0s5pJ2MUj6lslntifSSlrgCCTKQucE"}],"authentication":{},"metaSortKey":-1742176908821,"isPrivate":false,"pathParameters":[],"settingStoreCookies":true,"settingSendCookies":true,"settingDisableRenderRequestBody":false,"settingEncodeUrl":true,"settingRebuildPath":true,"settingFollowRedirects":"global","_type":"request"},{"_id":"req_f57e6c8d5d0f4ea3a8869ee62a065aa7","parentId":"fld_7f7fecea9b6f4102991559e7aaf86b3e","modified":1742307906718,"created":1742252098495,"url":"http://localhost:8080/usuarios/cpf/222.654.987-00","name":"Consultar Usuario por CPF","description":"","method":"GET","body":{},"parameters":[],"headers":[{"name":"User-Agent","value":"insomnia/10.3.1"},{"name":"Authorization","value":"Bearer eyJhbGciOiJIUzI1NiJ9.eyJzdWIiOiJyaWNhcmRvLmp1c3Rpbm9AZXhlbXBsby5jb20iLCJpYXQiOjE3NDIzMDc1OTIsImV4cCI6MTc0MjM5Mzk5Mn0.wfVrflkPRjVDY0s5pJ2MUj6lslntifSSlrgCCTKQucE"}],"authentication":{},"metaSortKey":-1742252316059,"isPrivate":false,"pathParameters":[],"settingStoreCookies":true,"settingSendCookies":true,"settingDisableRenderRequestBody":false,"settingEncodeUrl":true,"settingRebuildPath":true,"settingFollowRedirects":"global","_type":"request"},{"_id":"fld_7f7fecea9b6f4102991559e7aaf86b3e","parentId":"fld_950421e50fd44584ad81b0d6adcc041a","modified":1742295142815,"created":1742252311824,"name":"Usuario","description":"","environment":{},"environmentPropertyOrder":null,"metaSortKey":-1742198409924.5,"environmentType":"kv","_type":"request_group"},{"_id":"env_2cb7c94c5908afc8ae40e4c0e02c72778383bd09","parentId":"wrk_ba408b070516419b801a2b64c181a5ae","modified":1742176762075,"created":1742176762075,"name":"Base Environment","data":{},"dataPropertyOrder":null,"color":null,"isPrivate":false,"metaSortKey":1742176762075,"environmentType":"kv","_type":"environment"},{"_id":"jar_2cb7c94c5908afc8ae40e4c0e02c72778383bd09","parentId":"wrk_ba408b070516419b801a2b64c181a5ae","modified":1742176762076,"created":1742176762076,"name":"Default Jar","cookies":[],"_type":"cookie_jar"}]}